{
  "info": {
    "_postman_id": "379bf5c4-0ec8-4019-9e16-ccd0caf22763",
    "name": "gotPuzzled",
    "schema": "https://schema.getpostman.com/json/collection/v2.1.0/collection.json",
    "_exporter_id": "48840201",
    "_collection_link": "https://go.postman.co/collection/48840201-379bf5c4-0ec8-4019-9e16-ccd0caf22763?source=collection_link"
  },
  "item": [
    {
      "name": "Users",
      "item": [
        {
          "name": "GetUserById",
          "request": {
            "method": "GET",
            "header": [
              {
                "key": "x-user-role",
                "value": "player",
                "type": "text"
              },
              {
                "key": "x-user-id",
                "value": "1",
                "type": "text"
              }
            ],
            "url": {
              "raw": "http://localhost:3000/users/1",
              "protocol": "http",
              "host": [
                "localhost"
              ],
              "port": "3000",
              "path": [
                "users",
                "1"
              ]
            }
          },
          "response": []
        },
        {
          "name": "GetAllUsers",
          "request": {
            "method": "GET",
            "header": [
              {
                "key": "x-user-role",
                "value": "admin",
                "type": "text"
              },
              {
                "key": "x-user-id",
                "value": "2",
                "type": "text"
              }
            ],
            "url": {
              "raw": "http://localhost:3000/users",
              "protocol": "http",
              "host": [
                "localhost"
              ],
              "port": "3000",
              "path": [
                "users"
              ]
            }
          },
          "response": []
        },
        {
          "name": "CreateUser",
          "request": {
            "method": "POST",
            "header": [],
            "body": {
              "mode": "raw",
              "raw": "{\r\n  \"firstName\": \"Israel\",\r\n  \"lastName\": \"Israeli\",\r\n  \"userRole\": \"player\"\r\n}",
              "options": {
                "raw": {
                  "language": "json"
                }
              }
            },
            "url": {
              "raw": "http://localhost:3000/users",
              "protocol": "http",
              "host": [
                "localhost"
              ],
              "port": "3000",
              "path": [
                "users"
              ]
            }
          },
          "response": []
        },
        {
          "name": "UpdateUser",
          "request": {
            "method": "PUT",
            "header": [
              {
                "key": "x-user-role",
                "value": "player",
                "type": "text"
              },
              {
                "key": "x-user-id",
                "value": "1",
                "type": "text"
              }
            ],
            "body": {
              "mode": "raw",
              "raw": "{\r\n  \"firstName\": \"Ben\",\r\n  \"lastName\": \"Smith\"\r\n}",
              "options": {
                "raw": {
                  "language": "json"
                }
              }
            },
            "url": {
              "raw": "http://localhost:3000/users/1",
              "protocol": "http",
              "host": [
                "localhost"
              ],
              "port": "3000",
              "path": [
                "users",
                "1"
              ]
            }
          },
          "response": []
        },
        {
          "name": "DeleteUser",
          "request": {
            "method": "DELETE",
            "header": [
              {
                "key": "x-user-role",
                "value": "player",
                "type": "text"
              },
              {
                "key": "x-user-id",
                "value": "5",
                "type": "text"
              }
            ],
            "url": {
              "raw": "http://localhost:3000/users/5",
              "protocol": "http",
              "host": [
                "localhost"
              ],
              "port": "3000",
              "path": [
                "users",
                "5"
              ]
            }
          },
          "response": []
        }
      ]
    },
    {
      "name": "Scores",
      "item": [
        {
          "name": "GetSpecificScore",
          "request": {
            "method": "GET",
            "header": [
              {
                "key": "x-user-role",
                "value": "player",
                "type": "text"
              },
              {
                "key": "x-user-id",
                "value": "1",
                "type": "text"
              }
            ],
            "url": {
              "raw": "http://localhost:3000/scores/1/9/1",
              "protocol": "http",
              "host": [
                "localhost"
              ],
              "port": "3000",
              "path": [
                "scores",
                "1",
                "9",
                "1"
              ]
            }
          },
          "response": []
        },
        {
          "name": "GetAllScores",
          "request": {
            "method": "GET",
            "header": [
              {
                "key": "x-user-role",
                "value": "admin",
                "type": "text"
              },
              {
                "key": "x-user-id",
                "value": "2",
                "type": "text"
              }
            ],
            "url": {
              "raw": "http://localhost:3000/scores",
              "protocol": "http",
              "host": [
                "localhost"
              ],
              "port": "3000",
              "path": [
                "scores"
              ]
            }
          },
          "response": []
        },
        {
          "name": "CreateScore",
          "request": {
            "method": "POST",
            "header": [
              {
                "key": "x-user-id",
                "value": "1",
                "type": "text"
              },
              {
                "key": "x-user-role",
                "value": "player",
                "type": "text"
              }
            ],
            "body": {
              "mode": "raw",
              "raw": "{\r\n  \"pieces\": 9,\r\n  \"rounds\": 2,\r\n  \"score\": \"00:00:44\"\r\n  }",
              "options": {
                "raw": {
                  "language": "json"
                }
              }
            },
            "url": {
              "raw": "http://localhost:3000/scores/1",
              "protocol": "http",
              "host": [
                "localhost"
              ],
              "port": "3000",
              "path": [
                "scores",
                "1"
              ]
            }
          },
          "response": []
        },
        {
          "name": "UpdateScore",
          "request": {
            "method": "PUT",
            "header": [
              {
                "key": "x-user-role",
                "value": "admin",
                "type": "text"
              },
              {
                "key": "x-user-id",
                "value": "2",
                "type": "text"
              }
            ],
            "body": {
              "mode": "raw",
              "raw": "{\r\n  \"pieces\": 25,\r\n  \"rounds\": 3,\r\n  \"score\":\"09:08:25\"\r\n  }",
              "options": {
                "raw": {
                  "language": "json"
                }
              }
            },
            "url": {
              "raw": "http://localhost:3000/scores/3",
              "protocol": "http",
              "host": [
                "localhost"
              ],
              "port": "3000",
              "path": [
                "scores",
                "3"
              ]
            }
          },
          "response": []
        },
        {
          "name": "GetScoresById",
          "request": {
            "method": "GET",
            "header": [
              {
                "key": "x-user-role",
                "value": "player",
                "type": "text"
              },
              {
                "key": "x-user-id",
                "value": "1",
                "type": "text"
              }
            ],
            "url": {
              "raw": "http://localhost:3000/scores/1",
              "protocol": "http",
              "host": [
                "localhost"
              ],
              "port": "3000",
              "path": [
                "scores",
                "1"
              ]
            }
          },
          "response": []
        }
      ]
    },
    {
      "name": "HomeScreen",
      "request": {
        "method": "GET",
        "header": []
      },
      "response": []
    }
  ]
}